oled_text/Layout32.py
oled_text/Layout64.py
oled_text/__init__.py
oled_text/examples_32.py
oled_text/examples_64.py
oled_text/layout32.py
oled_text/layout64.py
oled_text/oled_text.py
oled_text/fonts/Arimo.ttf
oled_text/fonts/Crisp.ttf
oled_text/fonts/FontAwesomeRegular.ttf
oled_text/fonts/FontAwesomeSolid.ttf
oled_text/fonts/FreeMono.ttf
oled_text/fonts/FreeSans.ttf
oled_text/fonts/ProggyClean.ttf
oled_text/fonts/ProggySquare.ttf
oled_text/fonts/ProggyTiny.ttf
oled_text-1.2.3.dist-info/LICENSE.txt
oled_text-1.2.3.dist-info/METADATA
oled_text-1.2.3.dist-info/WHEEL
oled_text-1.2.3.dist-info/top_level.txt
oled_text-1.2.3.dist-info/RECORD
