Metadata-Version: 2.1
Name: oled-text
Version: 1.2.3
Summary: Easily display text on an SSD1306 oled display connected to a Raspberry Pi
Home-page: https://bitbucket.org/bachi76/oled-ssd1306-text/src
Author: Martin Bachmann
Author-email: m.bachmann@insign.ch
License: Apache 2.0
Keywords: OLED,SSD1306,Raspberry Pi
Platform: UNKNOWN
Requires-Python: >=3.5
